mkla/__init__.py
mkla/test.py
mkla-0.0.3.dist-info/METADATA
mkla-0.0.3.dist-info/WHEEL
mkla-0.0.3.dist-info/top_level.txt
mkla-0.0.3.dist-info/RECORD
